rackfish/__init__.py
rackfish/client.py
rackfish-1.0.3.dist-info/licenses/LICENSE
rackfish-1.0.3.dist-info/METADATA
rackfish-1.0.3.dist-info/WHEEL
rackfish-1.0.3.dist-info/top_level.txt
rackfish-1.0.3.dist-info/RECORD
