Metadata-Version: 2.4
Name: rackfish
Version: 1.0.3
Summary: A lightweight, dynamic Python client for Redfish BMC APIs
Author-email: Dmitrii Frolov <thefrolov@mts.ru>
License: MIT
Project-URL: Homepage, https://github.com/thefrolov/rackfish
Project-URL: Documentation, https://github.com/thefrolov/rackfish/blob/main/docs/INDEX.md
Project-URL: Repository, https://github.com/thefrolov/rackfish
Project-URL: Issues, https://github.com/thefrolov/rackfish/issues
Project-URL: Changelog, https://github.com/thefrolov/rackfish/blob/main/CHANGELOG.md
Keywords: redfish,bmc,ipmi,server-management,hardware-management,datacenter,ilo,idrac,server
Classifier: Development Status :: 5 - Production/Stable
Classifier: Intended Audience :: Developers
Classifier: Intended Audience :: System Administrators
Classifier: License :: OSI Approved :: MIT License
Classifier: Operating System :: OS Independent
Classifier: Programming Language :: Python :: 3
Classifier: Programming Language :: Python :: 3.8
Classifier: Programming Language :: Python :: 3.9
Classifier: Programming Language :: Python :: 3.10
Classifier: Programming Language :: Python :: 3.11
Classifier: Programming Language :: Python :: 3.12
Classifier: Topic :: Software Development :: Libraries :: Python Modules
Classifier: Topic :: System :: Hardware
Classifier: Topic :: System :: Systems Administration
Requires-Python: >=3.8
License-File: LICENSE
Requires-Dist: requests>=2.25.0
Provides-Extra: dev
Requires-Dist: pytest>=7.0; extra == "dev"
Requires-Dist: pytest-cov>=4.0; extra == "dev"
Requires-Dist: black>=23.0; extra == "dev"
Requires-Dist: ruff>=0.1.0; extra == "dev"
Requires-Dist: mypy>=1.0; extra == "dev"
Dynamic: license-file
